<stg><name>slide_window</name>


<trans_list>

<trans id="61" from="1" to="2">
<condition id="-1">
<or_exp><and_exp></and_exp></or_exp>
</condition>
</trans>

<trans id="62" from="2" to="3">
<condition id="-1">
<or_exp><and_exp></and_exp></or_exp>
</condition>
</trans>

<trans id="63" from="3" to="4">
<condition id="-1">
<or_exp><and_exp></and_exp></or_exp>
</condition>
</trans>
</trans_list>



<state_list>

<state id="1" st_id="1">

<operation id="5" st_id="1" stage="1" lat="1">
<core>NULL</core>
<MemPortIdVec></MemPortIdVec>
<condition id="-1">
<or_exp><and_exp></and_exp></or_exp>
</condition>

<Node id="6" bw="4" op_0_bw="4" op_1_bw="4">
<![CDATA[
.preheader.preheader.0:0  %line_buff_val_V_offs = call i4 @_ssdm_op_Read.ap_auto.i4(i4 %line_buff_val_V_offset)

]]></Node>
<StgValue><ssdm name="line_buff_val_V_offs"/></StgValue>
</operation>

<operation id="6" st_id="1" stage="1" lat="1">
<core>NULL</core>
<MemPortIdVec></MemPortIdVec>
<condition id="-1">
<or_exp><and_exp></and_exp></or_exp>
</condition>

<Node id="8" bw="13" op_0_bw="4">
<![CDATA[
.preheader.preheader.0:2  %zext_ln259 = zext i4 %line_buff_val_V_offs to i13

]]></Node>
<StgValue><ssdm name="zext_ln259"/></StgValue>
</operation>

<operation id="7" st_id="1" stage="1" lat="1">
<core>Mul</core>
<MemPortIdVec></MemPortIdVec>
<condition id="-1">
<or_exp><and_exp></and_exp></or_exp>
</condition>

<Node id="9" bw="13" op_0_bw="13" op_1_bw="13">
<![CDATA[
.preheader.preheader.0:3  %mul_ln259 = mul i13 %zext_ln259, 418

]]></Node>
<StgValue><ssdm name="mul_ln259"/></StgValue>
</operation>
</state>

<state id="2" st_id="2">

<operation id="8" st_id="2" stage="1" lat="1">
<core>NULL</core>
<MemPortIdVec></MemPortIdVec>
<condition id="-1">
<or_exp><and_exp></and_exp></or_exp>
</condition>

<Node id="7" bw="9" op_0_bw="9" op_1_bw="9">
<![CDATA[
.preheader.preheader.0:1  %conv_count_read = call i9 @_ssdm_op_Read.ap_auto.i9(i9 %conv_count)

]]></Node>
<StgValue><ssdm name="conv_count_read"/></StgValue>
</operation>

<operation id="9" st_id="2" stage="1" lat="1">
<core>NULL</core>
<MemPortIdVec></MemPortIdVec>
<condition id="-1">
<or_exp><and_exp></and_exp></or_exp>
</condition>

<Node id="10" bw="13" op_0_bw="9">
<![CDATA[
.preheader.preheader.0:4  %zext_ln259_1 = zext i9 %conv_count_read to i13

]]></Node>
<StgValue><ssdm name="zext_ln259_1"/></StgValue>
</operation>

<operation id="10" st_id="2" stage="1" lat="1">
<core>AddSub</core>
<MemPortIdVec></MemPortIdVec>
<condition id="-1">
<or_exp><and_exp></and_exp></or_exp>
</condition>

<Node id="11" bw="13" op_0_bw="13" op_1_bw="13">
<![CDATA[
.preheader.preheader.0:5  %add_ln259_2 = add i13 %zext_ln259_1, %mul_ln259

]]></Node>
<StgValue><ssdm name="add_ln259_2"/></StgValue>
</operation>

<operation id="11" st_id="2" stage="1" lat="1">
<core>NULL</core>
<MemPortIdVec></MemPortIdVec>
<condition id="-1">
<or_exp><and_exp></and_exp></or_exp>
</condition>

<Node id="12" bw="64" op_0_bw="13">
<![CDATA[
.preheader.preheader.0:6  %sext_ln259 = sext i13 %add_ln259_2 to i64

]]></Node>
<StgValue><ssdm name="sext_ln259"/></StgValue>
</operation>

<operation id="12" st_id="2" stage="1" lat="1">
<core>NULL</core>
<MemPortIdVec></MemPortIdVec>
<condition id="-1">
<or_exp><and_exp></and_exp></or_exp>
</condition>

<Node id="13" bw="12" op_0_bw="16" op_1_bw="64" op_2_bw="64">
<![CDATA[
.preheader.preheader.0:7  %line_buff_val_0_V_a = getelementptr [3344 x i16]* %line_buff_val_0_V, i64 0, i64 %sext_ln259

]]></Node>
<StgValue><ssdm name="line_buff_val_0_V_a"/></StgValue>
</operation>

<operation id="13" st_id="2" stage="1" lat="1">
<core>NULL</core>
<MemPortIdVec></MemPortIdVec>
<condition id="-1">
<or_exp><and_exp></and_exp></or_exp>
</condition>

<Node id="14" bw="12" op_0_bw="16" op_1_bw="64" op_2_bw="64">
<![CDATA[
.preheader.preheader.0:8  %line_buff_val_1_V_a = getelementptr [3344 x i16]* %line_buff_val_1_V, i64 0, i64 %sext_ln259

]]></Node>
<StgValue><ssdm name="line_buff_val_1_V_a"/></StgValue>
</operation>

<operation id="14" st_id="2" stage="1" lat="1">
<core>NULL</core>
<MemPortIdVec></MemPortIdVec>
<condition id="-1">
<or_exp><and_exp></and_exp></or_exp>
</condition>

<Node id="15" bw="12" op_0_bw="16" op_1_bw="64" op_2_bw="64">
<![CDATA[
.preheader.preheader.0:9  %line_buff_val_2_V_a = getelementptr [3344 x i16]* %line_buff_val_2_V, i64 0, i64 %sext_ln259

]]></Node>
<StgValue><ssdm name="line_buff_val_2_V_a"/></StgValue>
</operation>

<operation id="15" st_id="2" stage="2" lat="2">
<core>RAM</core>
<MemPortIdVec>0 </MemPortIdVec>
<condition id="-1">
<or_exp><and_exp></and_exp></or_exp>
</condition>

<Node id="16" bw="16" op_0_bw="12">
<![CDATA[
.preheader.preheader.0:10  %line_buff_val_0_V_l = load i16* %line_buff_val_0_V_a, align 2

]]></Node>
<StgValue><ssdm name="line_buff_val_0_V_l"/></StgValue>
</operation>

<operation id="16" st_id="2" stage="1" lat="1">
<core>AddSub</core>
<MemPortIdVec></MemPortIdVec>
<condition id="-1">
<or_exp><and_exp></and_exp></or_exp>
</condition>

<Node id="17" bw="9" op_0_bw="9" op_1_bw="9">
<![CDATA[
.preheader.preheader.0:11  %add_ln259 = add i9 %conv_count_read, 1

]]></Node>
<StgValue><ssdm name="add_ln259"/></StgValue>
</operation>

<operation id="17" st_id="2" stage="1" lat="1">
<core>NULL</core>
<MemPortIdVec></MemPortIdVec>
<condition id="-1">
<or_exp><and_exp></and_exp></or_exp>
</condition>

<Node id="18" bw="13" op_0_bw="9">
<![CDATA[
.preheader.preheader.0:12  %zext_ln259_2 = zext i9 %add_ln259 to i13

]]></Node>
<StgValue><ssdm name="zext_ln259_2"/></StgValue>
</operation>

<operation id="18" st_id="2" stage="1" lat="1">
<core>AddSub</core>
<MemPortIdVec></MemPortIdVec>
<condition id="-1">
<or_exp><and_exp></and_exp></or_exp>
</condition>

<Node id="19" bw="13" op_0_bw="13" op_1_bw="13">
<![CDATA[
.preheader.preheader.0:13  %add_ln259_3 = add i13 %zext_ln259_2, %mul_ln259

]]></Node>
<StgValue><ssdm name="add_ln259_3"/></StgValue>
</operation>

<operation id="19" st_id="2" stage="1" lat="1">
<core>NULL</core>
<MemPortIdVec></MemPortIdVec>
<condition id="-1">
<or_exp><and_exp></and_exp></or_exp>
</condition>

<Node id="20" bw="64" op_0_bw="13">
<![CDATA[
.preheader.preheader.0:14  %sext_ln259_1 = sext i13 %add_ln259_3 to i64

]]></Node>
<StgValue><ssdm name="sext_ln259_1"/></StgValue>
</operation>

<operation id="20" st_id="2" stage="1" lat="1">
<core>NULL</core>
<MemPortIdVec></MemPortIdVec>
<condition id="-1">
<or_exp><and_exp></and_exp></or_exp>
</condition>

<Node id="21" bw="12" op_0_bw="16" op_1_bw="64" op_2_bw="64">
<![CDATA[
.preheader.preheader.0:15  %line_buff_val_0_V_a_1 = getelementptr [3344 x i16]* %line_buff_val_0_V, i64 0, i64 %sext_ln259_1

]]></Node>
<StgValue><ssdm name="line_buff_val_0_V_a_1"/></StgValue>
</operation>

<operation id="21" st_id="2" stage="1" lat="1">
<core>NULL</core>
<MemPortIdVec></MemPortIdVec>
<condition id="-1">
<or_exp><and_exp></and_exp></or_exp>
</condition>

<Node id="22" bw="12" op_0_bw="16" op_1_bw="64" op_2_bw="64">
<![CDATA[
.preheader.preheader.0:16  %line_buff_val_1_V_a_1 = getelementptr [3344 x i16]* %line_buff_val_1_V, i64 0, i64 %sext_ln259_1

]]></Node>
<StgValue><ssdm name="line_buff_val_1_V_a_1"/></StgValue>
</operation>

<operation id="22" st_id="2" stage="1" lat="1">
<core>NULL</core>
<MemPortIdVec></MemPortIdVec>
<condition id="-1">
<or_exp><and_exp></and_exp></or_exp>
</condition>

<Node id="23" bw="12" op_0_bw="16" op_1_bw="64" op_2_bw="64">
<![CDATA[
.preheader.preheader.0:17  %line_buff_val_2_V_a_1 = getelementptr [3344 x i16]* %line_buff_val_2_V, i64 0, i64 %sext_ln259_1

]]></Node>
<StgValue><ssdm name="line_buff_val_2_V_a_1"/></StgValue>
</operation>

<operation id="23" st_id="2" stage="2" lat="2">
<core>RAM</core>
<MemPortIdVec>1 </MemPortIdVec>
<condition id="-1">
<or_exp><and_exp></and_exp></or_exp>
</condition>

<Node id="24" bw="16" op_0_bw="12">
<![CDATA[
.preheader.preheader.0:18  %line_buff_val_0_V_l_1 = load i16* %line_buff_val_0_V_a_1, align 2

]]></Node>
<StgValue><ssdm name="line_buff_val_0_V_l_1"/></StgValue>
</operation>

<operation id="24" st_id="2" stage="1" lat="1">
<core>AddSub</core>
<MemPortIdVec></MemPortIdVec>
<condition id="-1">
<or_exp><and_exp></and_exp></or_exp>
</condition>

<Node id="25" bw="9" op_0_bw="9" op_1_bw="9">
<![CDATA[
.preheader.preheader.0:19  %add_ln259_1 = add i9 %conv_count_read, 2

]]></Node>
<StgValue><ssdm name="add_ln259_1"/></StgValue>
</operation>

<operation id="25" st_id="2" stage="1" lat="1">
<core>NULL</core>
<MemPortIdVec></MemPortIdVec>
<condition id="-1">
<or_exp><and_exp></and_exp></or_exp>
</condition>

<Node id="26" bw="13" op_0_bw="9">
<![CDATA[
.preheader.preheader.0:20  %zext_ln259_3 = zext i9 %add_ln259_1 to i13

]]></Node>
<StgValue><ssdm name="zext_ln259_3"/></StgValue>
</operation>

<operation id="26" st_id="2" stage="1" lat="1">
<core>AddSub</core>
<MemPortIdVec></MemPortIdVec>
<condition id="-1">
<or_exp><and_exp></and_exp></or_exp>
</condition>

<Node id="27" bw="13" op_0_bw="13" op_1_bw="13">
<![CDATA[
.preheader.preheader.0:21  %add_ln259_4 = add i13 %zext_ln259_3, %mul_ln259

]]></Node>
<StgValue><ssdm name="add_ln259_4"/></StgValue>
</operation>

<operation id="27" st_id="2" stage="2" lat="2">
<core>RAM</core>
<MemPortIdVec>0 </MemPortIdVec>
<condition id="-1">
<or_exp><and_exp></and_exp></or_exp>
</condition>

<Node id="33" bw="16" op_0_bw="12">
<![CDATA[
.preheader.preheader.0:27  %line_buff_val_1_V_l = load i16* %line_buff_val_1_V_a, align 2

]]></Node>
<StgValue><ssdm name="line_buff_val_1_V_l"/></StgValue>
</operation>

<operation id="28" st_id="2" stage="2" lat="2">
<core>RAM</core>
<MemPortIdVec>1 </MemPortIdVec>
<condition id="-1">
<or_exp><and_exp></and_exp></or_exp>
</condition>

<Node id="34" bw="16" op_0_bw="12">
<![CDATA[
.preheader.preheader.0:28  %line_buff_val_1_V_l_1 = load i16* %line_buff_val_1_V_a_1, align 2

]]></Node>
<StgValue><ssdm name="line_buff_val_1_V_l_1"/></StgValue>
</operation>

<operation id="29" st_id="2" stage="2" lat="2">
<core>RAM</core>
<MemPortIdVec>0 </MemPortIdVec>
<condition id="-1">
<or_exp><and_exp></and_exp></or_exp>
</condition>

<Node id="36" bw="16" op_0_bw="12">
<![CDATA[
.preheader.preheader.0:30  %line_buff_val_2_V_l = load i16* %line_buff_val_2_V_a, align 2

]]></Node>
<StgValue><ssdm name="line_buff_val_2_V_l"/></StgValue>
</operation>

<operation id="30" st_id="2" stage="2" lat="2">
<core>RAM</core>
<MemPortIdVec>1 </MemPortIdVec>
<condition id="-1">
<or_exp><and_exp></and_exp></or_exp>
</condition>

<Node id="37" bw="16" op_0_bw="12">
<![CDATA[
.preheader.preheader.0:31  %line_buff_val_2_V_l_1 = load i16* %line_buff_val_2_V_a_1, align 2

]]></Node>
<StgValue><ssdm name="line_buff_val_2_V_l_1"/></StgValue>
</operation>
</state>

<state id="3" st_id="3">

<operation id="31" st_id="3" stage="1" lat="2">
<core>RAM</core>
<MemPortIdVec>0 </MemPortIdVec>
<condition id="-1">
<or_exp><and_exp></and_exp></or_exp>
</condition>

<Node id="16" bw="16" op_0_bw="12">
<![CDATA[
.preheader.preheader.0:10  %line_buff_val_0_V_l = load i16* %line_buff_val_0_V_a, align 2

]]></Node>
<StgValue><ssdm name="line_buff_val_0_V_l"/></StgValue>
</operation>

<operation id="32" st_id="3" stage="1" lat="2">
<core>RAM</core>
<MemPortIdVec>1 </MemPortIdVec>
<condition id="-1">
<or_exp><and_exp></and_exp></or_exp>
</condition>

<Node id="24" bw="16" op_0_bw="12">
<![CDATA[
.preheader.preheader.0:18  %line_buff_val_0_V_l_1 = load i16* %line_buff_val_0_V_a_1, align 2

]]></Node>
<StgValue><ssdm name="line_buff_val_0_V_l_1"/></StgValue>
</operation>

<operation id="33" st_id="3" stage="1" lat="1">
<core>NULL</core>
<MemPortIdVec></MemPortIdVec>
<condition id="-1">
<or_exp><and_exp></and_exp></or_exp>
</condition>

<Node id="28" bw="64" op_0_bw="13">
<![CDATA[
.preheader.preheader.0:22  %sext_ln259_2 = sext i13 %add_ln259_4 to i64

]]></Node>
<StgValue><ssdm name="sext_ln259_2"/></StgValue>
</operation>

<operation id="34" st_id="3" stage="1" lat="1">
<core>NULL</core>
<MemPortIdVec></MemPortIdVec>
<condition id="-1">
<or_exp><and_exp></and_exp></or_exp>
</condition>

<Node id="29" bw="12" op_0_bw="16" op_1_bw="64" op_2_bw="64">
<![CDATA[
.preheader.preheader.0:23  %line_buff_val_0_V_a_2 = getelementptr [3344 x i16]* %line_buff_val_0_V, i64 0, i64 %sext_ln259_2

]]></Node>
<StgValue><ssdm name="line_buff_val_0_V_a_2"/></StgValue>
</operation>

<operation id="35" st_id="3" stage="1" lat="1">
<core>NULL</core>
<MemPortIdVec></MemPortIdVec>
<condition id="-1">
<or_exp><and_exp></and_exp></or_exp>
</condition>

<Node id="30" bw="12" op_0_bw="16" op_1_bw="64" op_2_bw="64">
<![CDATA[
.preheader.preheader.0:24  %line_buff_val_1_V_a_2 = getelementptr [3344 x i16]* %line_buff_val_1_V, i64 0, i64 %sext_ln259_2

]]></Node>
<StgValue><ssdm name="line_buff_val_1_V_a_2"/></StgValue>
</operation>

<operation id="36" st_id="3" stage="1" lat="1">
<core>NULL</core>
<MemPortIdVec></MemPortIdVec>
<condition id="-1">
<or_exp><and_exp></and_exp></or_exp>
</condition>

<Node id="31" bw="12" op_0_bw="16" op_1_bw="64" op_2_bw="64">
<![CDATA[
.preheader.preheader.0:25  %line_buff_val_2_V_a_2 = getelementptr [3344 x i16]* %line_buff_val_2_V, i64 0, i64 %sext_ln259_2

]]></Node>
<StgValue><ssdm name="line_buff_val_2_V_a_2"/></StgValue>
</operation>

<operation id="37" st_id="3" stage="2" lat="2">
<core>RAM</core>
<MemPortIdVec>0 </MemPortIdVec>
<condition id="-1">
<or_exp><and_exp></and_exp></or_exp>
</condition>

<Node id="32" bw="16" op_0_bw="12">
<![CDATA[
.preheader.preheader.0:26  %line_buff_val_0_V_l_2 = load i16* %line_buff_val_0_V_a_2, align 2

]]></Node>
<StgValue><ssdm name="line_buff_val_0_V_l_2"/></StgValue>
</operation>

<operation id="38" st_id="3" stage="1" lat="2">
<core>RAM</core>
<MemPortIdVec>0 </MemPortIdVec>
<condition id="-1">
<or_exp><and_exp></and_exp></or_exp>
</condition>

<Node id="33" bw="16" op_0_bw="12">
<![CDATA[
.preheader.preheader.0:27  %line_buff_val_1_V_l = load i16* %line_buff_val_1_V_a, align 2

]]></Node>
<StgValue><ssdm name="line_buff_val_1_V_l"/></StgValue>
</operation>

<operation id="39" st_id="3" stage="1" lat="2">
<core>RAM</core>
<MemPortIdVec>1 </MemPortIdVec>
<condition id="-1">
<or_exp><and_exp></and_exp></or_exp>
</condition>

<Node id="34" bw="16" op_0_bw="12">
<![CDATA[
.preheader.preheader.0:28  %line_buff_val_1_V_l_1 = load i16* %line_buff_val_1_V_a_1, align 2

]]></Node>
<StgValue><ssdm name="line_buff_val_1_V_l_1"/></StgValue>
</operation>

<operation id="40" st_id="3" stage="2" lat="2">
<core>RAM</core>
<MemPortIdVec>0 </MemPortIdVec>
<condition id="-1">
<or_exp><and_exp></and_exp></or_exp>
</condition>

<Node id="35" bw="16" op_0_bw="12">
<![CDATA[
.preheader.preheader.0:29  %line_buff_val_1_V_l_2 = load i16* %line_buff_val_1_V_a_2, align 2

]]></Node>
<StgValue><ssdm name="line_buff_val_1_V_l_2"/></StgValue>
</operation>

<operation id="41" st_id="3" stage="1" lat="2">
<core>RAM</core>
<MemPortIdVec>0 </MemPortIdVec>
<condition id="-1">
<or_exp><and_exp></and_exp></or_exp>
</condition>

<Node id="36" bw="16" op_0_bw="12">
<![CDATA[
.preheader.preheader.0:30  %line_buff_val_2_V_l = load i16* %line_buff_val_2_V_a, align 2

]]></Node>
<StgValue><ssdm name="line_buff_val_2_V_l"/></StgValue>
</operation>

<operation id="42" st_id="3" stage="1" lat="2">
<core>RAM</core>
<MemPortIdVec>1 </MemPortIdVec>
<condition id="-1">
<or_exp><and_exp></and_exp></or_exp>
</condition>

<Node id="37" bw="16" op_0_bw="12">
<![CDATA[
.preheader.preheader.0:31  %line_buff_val_2_V_l_1 = load i16* %line_buff_val_2_V_a_1, align 2

]]></Node>
<StgValue><ssdm name="line_buff_val_2_V_l_1"/></StgValue>
</operation>

<operation id="43" st_id="3" stage="2" lat="2">
<core>RAM</core>
<MemPortIdVec>0 </MemPortIdVec>
<condition id="-1">
<or_exp><and_exp></and_exp></or_exp>
</condition>

<Node id="38" bw="16" op_0_bw="12">
<![CDATA[
.preheader.preheader.0:32  %line_buff_val_2_V_l_2 = load i16* %line_buff_val_2_V_a_2, align 2

]]></Node>
<StgValue><ssdm name="line_buff_val_2_V_l_2"/></StgValue>
</operation>
</state>

<state id="4" st_id="4">

<operation id="44" st_id="4" stage="1" lat="2">
<core>RAM</core>
<MemPortIdVec>0 </MemPortIdVec>
<condition id="-1">
<or_exp><and_exp></and_exp></or_exp>
</condition>

<Node id="32" bw="16" op_0_bw="12">
<![CDATA[
.preheader.preheader.0:26  %line_buff_val_0_V_l_2 = load i16* %line_buff_val_0_V_a_2, align 2

]]></Node>
<StgValue><ssdm name="line_buff_val_0_V_l_2"/></StgValue>
</operation>

<operation id="45" st_id="4" stage="1" lat="2">
<core>RAM</core>
<MemPortIdVec>0 </MemPortIdVec>
<condition id="-1">
<or_exp><and_exp></and_exp></or_exp>
</condition>

<Node id="35" bw="16" op_0_bw="12">
<![CDATA[
.preheader.preheader.0:29  %line_buff_val_1_V_l_2 = load i16* %line_buff_val_1_V_a_2, align 2

]]></Node>
<StgValue><ssdm name="line_buff_val_1_V_l_2"/></StgValue>
</operation>

<operation id="46" st_id="4" stage="1" lat="2">
<core>RAM</core>
<MemPortIdVec>0 </MemPortIdVec>
<condition id="-1">
<or_exp><and_exp></and_exp></or_exp>
</condition>

<Node id="38" bw="16" op_0_bw="12">
<![CDATA[
.preheader.preheader.0:32  %line_buff_val_2_V_l_2 = load i16* %line_buff_val_2_V_a_2, align 2

]]></Node>
<StgValue><ssdm name="line_buff_val_2_V_l_2"/></StgValue>
</operation>

<operation id="47" st_id="4" stage="1" lat="1">
<core>NULL</core>
<MemPortIdVec></MemPortIdVec>
<condition id="-1">
<or_exp><and_exp></and_exp></or_exp>
</condition>

<Node id="39" bw="144" op_0_bw="144" op_1_bw="16">
<![CDATA[
.preheader.preheader.0:33  %mrv = insertvalue { i16, i16, i16, i16, i16, i16, i16, i16, i16 } undef, i16 %line_buff_val_0_V_l, 0

]]></Node>
<StgValue><ssdm name="mrv"/></StgValue>
</operation>

<operation id="48" st_id="4" stage="1" lat="1">
<core>NULL</core>
<MemPortIdVec></MemPortIdVec>
<condition id="-1">
<or_exp><and_exp></and_exp></or_exp>
</condition>

<Node id="40" bw="144" op_0_bw="144" op_1_bw="16">
<![CDATA[
.preheader.preheader.0:34  %mrv_1 = insertvalue { i16, i16, i16, i16, i16, i16, i16, i16, i16 } %mrv, i16 %line_buff_val_0_V_l_1, 1

]]></Node>
<StgValue><ssdm name="mrv_1"/></StgValue>
</operation>

<operation id="49" st_id="4" stage="1" lat="1">
<core>NULL</core>
<MemPortIdVec></MemPortIdVec>
<condition id="-1">
<or_exp><and_exp></and_exp></or_exp>
</condition>

<Node id="41" bw="144" op_0_bw="144" op_1_bw="16">
<![CDATA[
.preheader.preheader.0:35  %mrv_2 = insertvalue { i16, i16, i16, i16, i16, i16, i16, i16, i16 } %mrv_1, i16 %line_buff_val_0_V_l_2, 2

]]></Node>
<StgValue><ssdm name="mrv_2"/></StgValue>
</operation>

<operation id="50" st_id="4" stage="1" lat="1">
<core>NULL</core>
<MemPortIdVec></MemPortIdVec>
<condition id="-1">
<or_exp><and_exp></and_exp></or_exp>
</condition>

<Node id="42" bw="144" op_0_bw="144" op_1_bw="16">
<![CDATA[
.preheader.preheader.0:36  %mrv_3 = insertvalue { i16, i16, i16, i16, i16, i16, i16, i16, i16 } %mrv_2, i16 %line_buff_val_1_V_l, 3

]]></Node>
<StgValue><ssdm name="mrv_3"/></StgValue>
</operation>

<operation id="51" st_id="4" stage="1" lat="1">
<core>NULL</core>
<MemPortIdVec></MemPortIdVec>
<condition id="-1">
<or_exp><and_exp></and_exp></or_exp>
</condition>

<Node id="43" bw="144" op_0_bw="144" op_1_bw="16">
<![CDATA[
.preheader.preheader.0:37  %mrv_4 = insertvalue { i16, i16, i16, i16, i16, i16, i16, i16, i16 } %mrv_3, i16 %line_buff_val_1_V_l_1, 4

]]></Node>
<StgValue><ssdm name="mrv_4"/></StgValue>
</operation>

<operation id="52" st_id="4" stage="1" lat="1">
<core>NULL</core>
<MemPortIdVec></MemPortIdVec>
<condition id="-1">
<or_exp><and_exp></and_exp></or_exp>
</condition>

<Node id="44" bw="144" op_0_bw="144" op_1_bw="16">
<![CDATA[
.preheader.preheader.0:38  %mrv_5 = insertvalue { i16, i16, i16, i16, i16, i16, i16, i16, i16 } %mrv_4, i16 %line_buff_val_1_V_l_2, 5

]]></Node>
<StgValue><ssdm name="mrv_5"/></StgValue>
</operation>

<operation id="53" st_id="4" stage="1" lat="1">
<core>NULL</core>
<MemPortIdVec></MemPortIdVec>
<condition id="-1">
<or_exp><and_exp></and_exp></or_exp>
</condition>

<Node id="45" bw="144" op_0_bw="144" op_1_bw="16">
<![CDATA[
.preheader.preheader.0:39  %mrv_6 = insertvalue { i16, i16, i16, i16, i16, i16, i16, i16, i16 } %mrv_5, i16 %line_buff_val_2_V_l, 6

]]></Node>
<StgValue><ssdm name="mrv_6"/></StgValue>
</operation>

<operation id="54" st_id="4" stage="1" lat="1">
<core>NULL</core>
<MemPortIdVec></MemPortIdVec>
<condition id="-1">
<or_exp><and_exp></and_exp></or_exp>
</condition>

<Node id="46" bw="144" op_0_bw="144" op_1_bw="16">
<![CDATA[
.preheader.preheader.0:40  %mrv_7 = insertvalue { i16, i16, i16, i16, i16, i16, i16, i16, i16 } %mrv_6, i16 %line_buff_val_2_V_l_1, 7

]]></Node>
<StgValue><ssdm name="mrv_7"/></StgValue>
</operation>

<operation id="55" st_id="4" stage="1" lat="1">
<core>NULL</core>
<MemPortIdVec></MemPortIdVec>
<condition id="-1">
<or_exp><and_exp></and_exp></or_exp>
</condition>

<Node id="47" bw="144" op_0_bw="144" op_1_bw="16">
<![CDATA[
.preheader.preheader.0:41  %mrv_8 = insertvalue { i16, i16, i16, i16, i16, i16, i16, i16, i16 } %mrv_7, i16 %line_buff_val_2_V_l_2, 8

]]></Node>
<StgValue><ssdm name="mrv_8"/></StgValue>
</operation>

<operation id="56" st_id="4" stage="1" lat="1">
<core>NULL</core>
<MemPortIdVec></MemPortIdVec>
<condition id="-1">
<or_exp><and_exp></and_exp></or_exp>
</condition>

<Node id="48" bw="0" op_0_bw="144">
<![CDATA[
.preheader.preheader.0:42  ret { i16, i16, i16, i16, i16, i16, i16, i16, i16 } %mrv_8

]]></Node>
<StgValue><ssdm name="ret_ln264"/></StgValue>
</operation>
</state>
</state_list>


<ports>
<port id="64" name="conv_count" dir="0" iftype="0">
<core>NULL</core><StgValue><ssdm name="conv_count"/></StgValue>
</port>
<port id="65" name="line_buff_val_0_V" dir="0" iftype="1">
<core>RAM</core><StgValue><ssdm name="line_buff_val_0_V"/><MemPortTyVec>1 1 </MemPortTyVec>
</StgValue>
</port>
<port id="66" name="line_buff_val_1_V" dir="0" iftype="1">
<core>RAM</core><StgValue><ssdm name="line_buff_val_1_V"/><MemPortTyVec>1 1 </MemPortTyVec>
</StgValue>
</port>
<port id="67" name="line_buff_val_2_V" dir="0" iftype="1">
<core>RAM</core><StgValue><ssdm name="line_buff_val_2_V"/><MemPortTyVec>1 1 </MemPortTyVec>
</StgValue>
</port>
<port id="68" name="line_buff_val_V_offset" dir="0" iftype="0">
<core>NULL</core><StgValue><ssdm name="line_buff_val_V_offset"/></StgValue>
</port>
</ports>


<dataflows>
<dataflow id="70" from="_ssdm_op_Read.ap_auto.i4" to="line_buff_val_V_offs" fromId="69" toId="5">
</dataflow>
<dataflow id="71" from="line_buff_val_V_offset" to="line_buff_val_V_offs" fromId="68" toId="5">
</dataflow>
<dataflow id="72" from="line_buff_val_V_offs" to="zext_ln259" fromId="5" toId="6">
</dataflow>
<dataflow id="73" from="zext_ln259" to="mul_ln259" fromId="6" toId="7">
</dataflow>
<dataflow id="75" from="StgValue_74" to="mul_ln259" fromId="74" toId="7">
</dataflow>
<dataflow id="77" from="_ssdm_op_Read.ap_auto.i9" to="conv_count_read" fromId="76" toId="8">
</dataflow>
<dataflow id="78" from="conv_count" to="conv_count_read" fromId="64" toId="8">
</dataflow>
<dataflow id="79" from="conv_count_read" to="zext_ln259_1" fromId="8" toId="9">
</dataflow>
<dataflow id="80" from="zext_ln259_1" to="add_ln259_2" fromId="9" toId="10">
</dataflow>
<dataflow id="81" from="mul_ln259" to="add_ln259_2" fromId="7" toId="10">
</dataflow>
<dataflow id="82" from="add_ln259_2" to="sext_ln259" fromId="10" toId="11">
</dataflow>
<dataflow id="83" from="line_buff_val_0_V" to="line_buff_val_0_V_a" fromId="65" toId="12">
</dataflow>
<dataflow id="85" from="StgValue_84" to="line_buff_val_0_V_a" fromId="84" toId="12">
</dataflow>
<dataflow id="86" from="sext_ln259" to="line_buff_val_0_V_a" fromId="11" toId="12">
</dataflow>
<dataflow id="87" from="line_buff_val_1_V" to="line_buff_val_1_V_a" fromId="66" toId="13">
</dataflow>
<dataflow id="88" from="StgValue_84" to="line_buff_val_1_V_a" fromId="84" toId="13">
</dataflow>
<dataflow id="89" from="sext_ln259" to="line_buff_val_1_V_a" fromId="11" toId="13">
</dataflow>
<dataflow id="90" from="line_buff_val_2_V" to="line_buff_val_2_V_a" fromId="67" toId="14">
</dataflow>
<dataflow id="91" from="StgValue_84" to="line_buff_val_2_V_a" fromId="84" toId="14">
</dataflow>
<dataflow id="92" from="sext_ln259" to="line_buff_val_2_V_a" fromId="11" toId="14">
</dataflow>
<dataflow id="93" from="line_buff_val_0_V_a" to="line_buff_val_0_V_l" fromId="12" toId="15">
</dataflow>
<dataflow id="94" from="conv_count_read" to="add_ln259" fromId="8" toId="16">
</dataflow>
<dataflow id="96" from="StgValue_95" to="add_ln259" fromId="95" toId="16">
</dataflow>
<dataflow id="97" from="add_ln259" to="zext_ln259_2" fromId="16" toId="17">
</dataflow>
<dataflow id="98" from="zext_ln259_2" to="add_ln259_3" fromId="17" toId="18">
</dataflow>
<dataflow id="99" from="mul_ln259" to="add_ln259_3" fromId="7" toId="18">
</dataflow>
<dataflow id="100" from="add_ln259_3" to="sext_ln259_1" fromId="18" toId="19">
</dataflow>
<dataflow id="101" from="line_buff_val_0_V" to="line_buff_val_0_V_a_1" fromId="65" toId="20">
</dataflow>
<dataflow id="102" from="StgValue_84" to="line_buff_val_0_V_a_1" fromId="84" toId="20">
</dataflow>
<dataflow id="103" from="sext_ln259_1" to="line_buff_val_0_V_a_1" fromId="19" toId="20">
</dataflow>
<dataflow id="104" from="line_buff_val_1_V" to="line_buff_val_1_V_a_1" fromId="66" toId="21">
</dataflow>
<dataflow id="105" from="StgValue_84" to="line_buff_val_1_V_a_1" fromId="84" toId="21">
</dataflow>
<dataflow id="106" from="sext_ln259_1" to="line_buff_val_1_V_a_1" fromId="19" toId="21">
</dataflow>
<dataflow id="107" from="line_buff_val_2_V" to="line_buff_val_2_V_a_1" fromId="67" toId="22">
</dataflow>
<dataflow id="108" from="StgValue_84" to="line_buff_val_2_V_a_1" fromId="84" toId="22">
</dataflow>
<dataflow id="109" from="sext_ln259_1" to="line_buff_val_2_V_a_1" fromId="19" toId="22">
</dataflow>
<dataflow id="110" from="line_buff_val_0_V_a_1" to="line_buff_val_0_V_l_1" fromId="20" toId="23">
</dataflow>
<dataflow id="111" from="conv_count_read" to="add_ln259_1" fromId="8" toId="24">
</dataflow>
<dataflow id="113" from="StgValue_112" to="add_ln259_1" fromId="112" toId="24">
</dataflow>
<dataflow id="114" from="add_ln259_1" to="zext_ln259_3" fromId="24" toId="25">
</dataflow>
<dataflow id="115" from="zext_ln259_3" to="add_ln259_4" fromId="25" toId="26">
</dataflow>
<dataflow id="116" from="mul_ln259" to="add_ln259_4" fromId="7" toId="26">
</dataflow>
<dataflow id="117" from="line_buff_val_1_V_a" to="line_buff_val_1_V_l" fromId="13" toId="27">
</dataflow>
<dataflow id="118" from="line_buff_val_1_V_a_1" to="line_buff_val_1_V_l_1" fromId="21" toId="28">
</dataflow>
<dataflow id="119" from="line_buff_val_2_V_a" to="line_buff_val_2_V_l" fromId="14" toId="29">
</dataflow>
<dataflow id="120" from="line_buff_val_2_V_a_1" to="line_buff_val_2_V_l_1" fromId="22" toId="30">
</dataflow>
<dataflow id="121" from="line_buff_val_0_V_a" to="line_buff_val_0_V_l" fromId="12" toId="31">
</dataflow>
<dataflow id="122" from="line_buff_val_0_V_a_1" to="line_buff_val_0_V_l_1" fromId="20" toId="32">
</dataflow>
<dataflow id="123" from="add_ln259_4" to="sext_ln259_2" fromId="26" toId="33">
</dataflow>
<dataflow id="124" from="line_buff_val_0_V" to="line_buff_val_0_V_a_2" fromId="65" toId="34">
</dataflow>
<dataflow id="125" from="StgValue_84" to="line_buff_val_0_V_a_2" fromId="84" toId="34">
</dataflow>
<dataflow id="126" from="sext_ln259_2" to="line_buff_val_0_V_a_2" fromId="33" toId="34">
</dataflow>
<dataflow id="127" from="line_buff_val_1_V" to="line_buff_val_1_V_a_2" fromId="66" toId="35">
</dataflow>
<dataflow id="128" from="StgValue_84" to="line_buff_val_1_V_a_2" fromId="84" toId="35">
</dataflow>
<dataflow id="129" from="sext_ln259_2" to="line_buff_val_1_V_a_2" fromId="33" toId="35">
</dataflow>
<dataflow id="130" from="line_buff_val_2_V" to="line_buff_val_2_V_a_2" fromId="67" toId="36">
</dataflow>
<dataflow id="131" from="StgValue_84" to="line_buff_val_2_V_a_2" fromId="84" toId="36">
</dataflow>
<dataflow id="132" from="sext_ln259_2" to="line_buff_val_2_V_a_2" fromId="33" toId="36">
</dataflow>
<dataflow id="133" from="line_buff_val_0_V_a_2" to="line_buff_val_0_V_l_2" fromId="34" toId="37">
</dataflow>
<dataflow id="134" from="line_buff_val_1_V_a" to="line_buff_val_1_V_l" fromId="13" toId="38">
</dataflow>
<dataflow id="135" from="line_buff_val_1_V_a_1" to="line_buff_val_1_V_l_1" fromId="21" toId="39">
</dataflow>
<dataflow id="136" from="line_buff_val_1_V_a_2" to="line_buff_val_1_V_l_2" fromId="35" toId="40">
</dataflow>
<dataflow id="137" from="line_buff_val_2_V_a" to="line_buff_val_2_V_l" fromId="14" toId="41">
</dataflow>
<dataflow id="138" from="line_buff_val_2_V_a_1" to="line_buff_val_2_V_l_1" fromId="22" toId="42">
</dataflow>
<dataflow id="139" from="line_buff_val_2_V_a_2" to="line_buff_val_2_V_l_2" fromId="36" toId="43">
</dataflow>
<dataflow id="140" from="line_buff_val_0_V_a_2" to="line_buff_val_0_V_l_2" fromId="34" toId="44">
</dataflow>
<dataflow id="141" from="line_buff_val_1_V_a_2" to="line_buff_val_1_V_l_2" fromId="35" toId="45">
</dataflow>
<dataflow id="142" from="line_buff_val_2_V_a_2" to="line_buff_val_2_V_l_2" fromId="36" toId="46">
</dataflow>
<dataflow id="144" from="StgValue_143" to="mrv" fromId="143" toId="47">
</dataflow>
<dataflow id="145" from="line_buff_val_0_V_l" to="mrv" fromId="31" toId="47">
</dataflow>
<dataflow id="146" from="mrv" to="mrv_1" fromId="47" toId="48">
</dataflow>
<dataflow id="147" from="line_buff_val_0_V_l_1" to="mrv_1" fromId="32" toId="48">
</dataflow>
<dataflow id="148" from="mrv_1" to="mrv_2" fromId="48" toId="49">
</dataflow>
<dataflow id="149" from="line_buff_val_0_V_l_2" to="mrv_2" fromId="44" toId="49">
</dataflow>
<dataflow id="150" from="mrv_2" to="mrv_3" fromId="49" toId="50">
</dataflow>
<dataflow id="151" from="line_buff_val_1_V_l" to="mrv_3" fromId="38" toId="50">
</dataflow>
<dataflow id="152" from="mrv_3" to="mrv_4" fromId="50" toId="51">
</dataflow>
<dataflow id="153" from="line_buff_val_1_V_l_1" to="mrv_4" fromId="39" toId="51">
</dataflow>
<dataflow id="154" from="mrv_4" to="mrv_5" fromId="51" toId="52">
</dataflow>
<dataflow id="155" from="line_buff_val_1_V_l_2" to="mrv_5" fromId="45" toId="52">
</dataflow>
<dataflow id="156" from="mrv_5" to="mrv_6" fromId="52" toId="53">
</dataflow>
<dataflow id="157" from="line_buff_val_2_V_l" to="mrv_6" fromId="41" toId="53">
</dataflow>
<dataflow id="158" from="mrv_6" to="mrv_7" fromId="53" toId="54">
</dataflow>
<dataflow id="159" from="line_buff_val_2_V_l_1" to="mrv_7" fromId="42" toId="54">
</dataflow>
<dataflow id="160" from="mrv_7" to="mrv_8" fromId="54" toId="55">
</dataflow>
<dataflow id="161" from="line_buff_val_2_V_l_2" to="mrv_8" fromId="46" toId="55">
</dataflow>
<dataflow id="162" from="mrv_8" to="ret_ln264" fromId="55" toId="56">
</dataflow>
</dataflows>


</stg>
